<?xml version="1.0" encoding="UTF-8"?>
<!DOCTYPE plist PUBLIC "-//Apple//DTD PLIST 1.0//EN" "http://www.apple.com/DTDs/PropertyList-1.0.dtd">
<plist version="1.0">
<dict>
	<key>Images</key>
	<array>
		<dict>
			<key>ImageIndex</key>
			<integer>42</integer>
			<key>NumberOfROIs</key>
			<integer>2</integer>
			<key>ROIs</key>
			<array>
				<dict>
					<key>Area</key>
					<real>0.013330383226275444</real>
					<key>Center</key>
					<string>(27.335133, -206.559723, -203.000000)</string>
					<key>Dev</key>
					<real>14.479049682617188</real>
					<key>IndexInImage</key>
					<integer>0</integer>
					<key>Length</key>
					<real>0.53265953063964844</real>
					<key>Max</key>
					<real>181</real>
					<key>Mean</key>
					<real>155.25</real>
					<key>Min</key>
					<real>136</real>
					<key>Name</key>
					<string>Left Anterior Descending Artery</string>
					<key>NumberOfPoints</key>
					<integer>12</integer>
					<key>Point_mm</key>
					<array>
						<string>(26.554342, -207.001953, -203.000000)</string>
						<string>(26.554342, -206.593750, -203.000000)</string>
						<string>(26.554342, -206.185547, -203.000000)</string>
						<string>(26.960938, -205.778946, -203.000000)</string>
						<string>(27.369141, -205.778946, -203.000000)</string>
						<string>(27.777344, -205.778946, -203.000000)</string>
						<string>(28.183952, -206.185547, -203.000000)</string>
						<string>(28.183952, -206.593750, -203.000000)</string>
						<string>(27.777344, -207.000351, -203.000000)</string>
						<string>(27.775749, -207.001953, -203.000000)</string>
						<string>(27.369141, -207.408554, -203.000000)</string>
						<string>(26.960938, -207.408554, -203.000000)</string>
					</array>
					<key>Point_px</key>
					<array>
						<string>(299.003922, 207.000000)</string>
						<string>(299.003922, 208.000000)</string>
						<string>(299.003922, 209.000000)</string>
						<string>(300.000000, 209.996078)</string>
						<string>(301.000000, 209.996078)</string>
						<string>(302.000000, 209.996078)</string>
						<string>(302.996078, 209.000000)</string>
						<string>(302.996078, 208.000000)</string>
						<string>(302.000000, 207.003922)</string>
						<string>(301.996078, 207.000000)</string>
						<string>(301.000000, 206.003922)</string>
						<string>(300.000000, 206.003922)</string>
					</array>
					<key>Total</key>
					<real>1242</real>
					<key>Type</key>
					<integer>20</integer>
				</dict>
				<dict>
					<key>Area</key>
					<real>0.013330383226275444</real>
					<key>Center</key>
					<string>(33.049976, -214.791824, -203.000000)</string>
					<key>Dev</key>
					<real>15.1651611328125</real>
					<key>IndexInImage</key>
					<integer>1</integer>
					<key>Length</key>
					<real>0.53265947103500366</real>
					<key>Max</key>
					<real>172</real>
					<key>Mean</key>
					<real>150.625</real>
					<key>Min</key>
					<real>132</real>
					<key>Name</key>
					<string>Left Anterior Descending Artery</string>
					<key>NumberOfPoints</key>
					<integer>12</integer>
					<key>Point_mm</key>
					<array>
						<string>(32.269184, -215.166016, -203.000000)</string>
						<string>(32.269184, -214.757812, -203.000000)</string>
						<string>(32.269184, -214.349609, -203.000000)</string>
						<string>(32.675781, -213.943008, -203.000000)</string>
						<string>(33.083984, -213.943008, -203.000000)</string>
						<string>(33.490593, -214.349609, -203.000000)</string>
						<string>(33.492188, -214.351212, -203.000000)</string>
						<string>(33.898796, -214.757812, -203.000000)</string>
						<string>(33.898796, -215.166016, -203.000000)</string>
						<string>(33.492188, -215.572617, -203.000000)</string>
						<string>(33.083984, -215.572617, -203.000000)</string>
						<string>(32.675781, -215.572617, -203.000000)</string>
					</array>
					<key>Point_px</key>
					<array>
						<string>(313.003922, 187.000000)</string>
						<string>(313.003922, 188.000000)</string>
						<string>(313.003922, 189.000000)</string>
						<string>(314.000000, 189.996078)</string>
						<string>(315.000000, 189.996078)</string>
						<string>(315.996078, 189.000000)</string>
						<string>(316.000000, 188.996078)</string>
						<string>(316.996078, 188.000000)</string>
						<string>(316.996078, 187.000000)</string>
						<string>(316.000000, 186.003922)</string>
						<string>(315.000000, 186.003922)</string>
						<string>(314.000000, 186.003922)</string>
					</array>
					<key>Total</key>
					<real>1205</real>
					<key>Type</key>
					<integer>20</integer>
				</dict>
			</array>
		</dict>
		<dict>
			<key>ImageIndex</key>
			<integer>43</integer>
			<key>NumberOfROIs</key>
			<integer>2</integer>
			<key>ROIs</key>
			<array>
				<dict>
					<key>Area</key>
					<real>0.0099977878853678703</real>
					<key>Center</key>
					<string>(22.470703, -204.348633, -200.000000)</string>
					<key>Dev</key>
					<real>6.0470376014709473</real>
					<key>IndexInImage</key>
					<integer>0</integer>
					<key>Length</key>
					<real>0.47493082284927368</real>
					<key>Max</key>
					<real>150</real>
					<key>Mean</key>
					<real>143.83332824707031</real>
					<key>Min</key>
					<real>134</real>
					<key>Name</key>
					<string>Left Anterior Descending Artery</string>
					<key>NumberOfPoints</key>
					<integer>10</integer>
					<key>Point_mm</key>
					<array>
						<string>(21.655905, -204.552734, -200.000000)</string>
						<string>(21.655905, -204.144531, -200.000000)</string>
						<string>(22.062500, -203.737930, -200.000000)</string>
						<string>(22.470703, -203.737930, -200.000000)</string>
						<string>(22.878906, -203.737930, -200.000000)</string>
						<string>(23.285515, -204.144531, -200.000000)</string>
						<string>(23.285515, -204.552734, -200.000000)</string>
						<string>(22.878906, -204.959335, -200.000000)</string>
						<string>(22.470703, -204.959335, -200.000000)</string>
						<string>(22.062500, -204.959335, -200.000000)</string>
					</array>
					<key>Point_px</key>
					<array>
						<string>(287.003922, 213.000000)</string>
						<string>(287.003922, 214.000000)</string>
						<string>(288.000000, 214.996078)</string>
						<string>(289.000000, 214.996078)</string>
						<string>(290.000000, 214.996078)</string>
						<string>(290.996078, 214.000000)</string>
						<string>(290.996078, 213.000000)</string>
						<string>(290.000000, 212.003922)</string>
						<string>(289.000000, 212.003922)</string>
						<string>(288.000000, 212.003922)</string>
					</array>
					<key>Total</key>
					<real>863</real>
					<key>Type</key>
					<integer>20</integer>
				</dict>
				<dict>
					<key>Area</key>
					<real>0.068318217992782593</real>
					<key>Center</key>
					<string>(27.835669, -207.818359, -200.000000)</string>
					<key>Dev</key>
					<real>95.642333984375</real>
					<key>IndexInImage</key>
					<integer>1</integer>
					<key>Length</key>
					<real>1.0662245750427246</real>
					<key>Max</key>
					<real>464</real>
					<key>Mean</key>
					<real>271.51220703125</real>
					<key>Min</key>
					<real>133</real>
					<key>Name</key>
					<string>Left Anterior Descending Artery</string>
					<key>NumberOfPoints</key>
					<integer>28</integer>
					<key>Point_mm</key>
					<array>
						<string>(26.962532, -209.042969, -200.000000)</string>
						<string>(26.960938, -209.041367, -200.000000)</string>
						<string>(26.554329, -208.634766, -200.000000)</string>
						<string>(26.552734, -208.633163, -200.000000)</string>
						<string>(26.146139, -208.226562, -200.000000)</string>
						<string>(26.146139, -207.818359, -200.000000)</string>
						<string>(26.146139, -207.410156, -200.000000)</string>
						<string>(26.552734, -207.003555, -200.000000)</string>
						<string>(26.554329, -207.001953, -200.000000)</string>
						<string>(26.960938, -206.595352, -200.000000)</string>
						<string>(26.962532, -206.593750, -200.000000)</string>
						<string>(27.369141, -206.187149, -200.000000)</string>
						<string>(27.777344, -206.187149, -200.000000)</string>
						<string>(28.185547, -206.187149, -200.000000)</string>
						<string>(28.593750, -206.187149, -200.000000)</string>
						<string>(29.000359, -206.593750, -200.000000)</string>
						<string>(29.001953, -206.595352, -200.000000)</string>
						<string>(29.408562, -207.001953, -200.000000)</string>
						<string>(29.408562, -207.410156, -200.000000)</string>
						<string>(29.408562, -207.818359, -200.000000)</string>
						<string>(29.408562, -208.226562, -200.000000)</string>
						<string>(29.408562, -208.634766, -200.000000)</string>
						<string>(29.001953, -209.041367, -200.000000)</string>
						<string>(29.000359, -209.042969, -200.000000)</string>
						<string>(28.593750, -209.449570, -200.000000)</string>
						<string>(28.185547, -209.449570, -200.000000)</string>
						<string>(27.777344, -209.449570, -200.000000)</string>
						<string>(27.369141, -209.449570, -200.000000)</string>
					</array>
					<key>Point_px</key>
					<array>
						<string>(300.003922, 202.000000)</string>
						<string>(300.000000, 202.003922)</string>
						<string>(299.003922, 203.000000)</string>
						<string>(299.000000, 203.003922)</string>
						<string>(298.003922, 204.000000)</string>
						<string>(298.003922, 205.000000)</string>
						<string>(298.003922, 206.000000)</string>
						<string>(299.000000, 206.996078)</string>
						<string>(299.003922, 207.000000)</string>
						<string>(300.000000, 207.996078)</string>
						<string>(300.003922, 208.000000)</string>
						<string>(301.000000, 208.996078)</string>
						<string>(302.000000, 208.996078)</string>
						<string>(303.000000, 208.996078)</string>
						<string>(304.000000, 208.996078)</string>
						<string>(304.996078, 208.000000)</string>
						<string>(305.000000, 207.996078)</string>
						<string>(305.996078, 207.000000)</string>
						<string>(305.996078, 206.000000)</string>
						<string>(305.996078, 205.000000)</string>
						<string>(305.996078, 204.000000)</string>
						<string>(305.996078, 203.000000)</string>
						<string>(305.000000, 202.003922)</string>
						<string>(304.996078, 202.000000)</string>
						<string>(304.000000, 201.003922)</string>
						<string>(303.000000, 201.003922)</string>
						<string>(302.000000, 201.003922)</string>
						<string>(301.000000, 201.003922)</string>
					</array>
					<key>Total</key>
					<real>11132</real>
					<key>Type</key>
					<integer>20</integer>
				</dict>
			</array>
		</dict>
		<dict>
			<key>ImageIndex</key>
			<integer>44</integer>
			<key>NumberOfROIs</key>
			<integer>1</integer>
			<key>ROIs</key>
			<array>
				<dict>
					<key>Area</key>
					<real>0.044990044087171555</real>
					<key>Center</key>
					<string>(12.830829, -198.884979, -197.000000)</string>
					<key>Dev</key>
					<real>70.314308166503906</real>
					<key>IndexInImage</key>
					<integer>0</integer>
					<key>Length</key>
					<real>0.96067196130752563</real>
					<key>Max</key>
					<real>360</real>
					<key>Mean</key>
					<real>232.22222900390625</real>
					<key>Min</key>
					<real>131</real>
					<key>Name</key>
					<string>Left Anterior Descending Artery</string>
					<key>NumberOfPoints</key>
					<integer>26</integer>
					<key>Point_mm</key>
					<array>
						<string>(11.859016, -199.654297, -197.000000)</string>
						<string>(11.857422, -199.652695, -197.000000)</string>
						<string>(11.450813, -199.246094, -197.000000)</string>
						<string>(11.450813, -198.837891, -197.000000)</string>
						<string>(11.449219, -198.836288, -197.000000)</string>
						<string>(11.042623, -198.429688, -197.000000)</string>
						<string>(11.449219, -198.023087, -197.000000)</string>
						<string>(11.450813, -198.021484, -197.000000)</string>
						<string>(11.857422, -197.614883, -197.000000)</string>
						<string>(12.265625, -197.614883, -197.000000)</string>
						<string>(12.673828, -197.614883, -197.000000)</string>
						<string>(13.080437, -198.021484, -197.000000)</string>
						<string>(13.082031, -198.023087, -197.000000)</string>
						<string>(13.490234, -198.023087, -197.000000)</string>
						<string>(13.896843, -198.429688, -197.000000)</string>
						<string>(13.898438, -198.431290, -197.000000)</string>
						<string>(14.305046, -198.837891, -197.000000)</string>
						<string>(14.306641, -198.839493, -197.000000)</string>
						<string>(14.713249, -199.246094, -197.000000)</string>
						<string>(14.306641, -199.652695, -197.000000)</string>
						<string>(14.305046, -199.654297, -197.000000)</string>
						<string>(13.898438, -200.060898, -197.000000)</string>
						<string>(13.490234, -200.060898, -197.000000)</string>
						<string>(13.082031, -200.060898, -197.000000)</string>
						<string>(12.673828, -200.060898, -197.000000)</string>
						<string>(12.265625, -200.060898, -197.000000)</string>
					</array>
					<key>Point_px</key>
					<array>
						<string>(263.003922, 225.000000)</string>
						<string>(263.000000, 225.003922)</string>
						<string>(262.003922, 226.000000)</string>
						<string>(262.003922, 227.000000)</string>
						<string>(262.000000, 227.003922)</string>
						<string>(261.003922, 228.000000)</string>
						<string>(262.000000, 228.996078)</string>
						<string>(262.003922, 229.000000)</string>
						<string>(263.000000, 229.996078)</string>
						<string>(264.000000, 229.996078)</string>
						<string>(265.000000, 229.996078)</string>
						<string>(265.996078, 229.000000)</string>
						<string>(266.000000, 228.996078)</string>
						<string>(267.000000, 228.996078)</string>
						<string>(267.996078, 228.000000)</string>
						<string>(268.000000, 227.996078)</string>
						<string>(268.996078, 227.000000)</string>
						<string>(269.000000, 226.996078)</string>
						<string>(269.996078, 226.000000)</string>
						<string>(269.000000, 225.003922)</string>
						<string>(268.996078, 225.000000)</string>
						<string>(268.000000, 224.003922)</string>
						<string>(267.000000, 224.003922)</string>
						<string>(266.000000, 224.003922)</string>
						<string>(265.000000, 224.003922)</string>
						<string>(264.000000, 224.003922)</string>
					</array>
					<key>Total</key>
					<real>6270</real>
					<key>Type</key>
					<integer>20</integer>
				</dict>
			</array>
		</dict>
	</array>
</dict>
</plist>
